CHANGES.md
LICENSE.txt
MANIFEST.in
README.md
setup.cfg
setup.py
navio/__init__.py
navio/meta_travis.py
navio/travis/__init__.py
navio/travis/_travis.py
navio_travis.egg-info/PKG-INFO
navio_travis.egg-info/SOURCES.txt
navio_travis.egg-info/dependency_links.txt
navio_travis.egg-info/top_level.txt