Metadata-Version: 2.1
Name: navio-travis
Version: 0.1.12
Summary: Travis CI helper libs
Home-page: https://oss.navio.online/navio-travis/
Author: Navio Online OpenSource projects
Author-email: oss@navio.online
License: Apache 2.0 license
Keywords: framework
Platform: UNKNOWN
Classifier: Development Status :: 4 - Beta
Classifier: Environment :: Console
Classifier: Intended Audience :: System Administrators
Classifier: Intended Audience :: Developers
Classifier: License :: OSI Approved :: Apache Software License
Classifier: Programming Language :: Python :: 2
Classifier: Programming Language :: Python :: 3
